argparse_enh/__init__.py
argparse_enh/argparse_enh.py
argparse_enh/argparse_shell.py
argparse_enh-0.0.4.dist-info/LICENSE
argparse_enh-0.0.4.dist-info/METADATA
argparse_enh-0.0.4.dist-info/WHEEL
argparse_enh-0.0.4.dist-info/top_level.txt
argparse_enh-0.0.4.dist-info/RECORD
