Metadata-Version: 2.1
Name: argparse-enh
Version: 0.0.4
Summary: Adds additional functionality to Argparse python library
Author-email: Vijaya Krishna Kasula <krishna.vijay4444@gmail.com>
Project-URL: Source Code, https://gitlab.com/argparse-enh/argparse-enh
Project-URL: Issues, https://gitlab.com/argparse-enh/argparse-enh/-/issues
Project-URL: Docs, https://argparse-enh.readthedocs.io/en/latest/
Keywords: argparse-api,argparse-gui,argparse-shell,argparse-bash,argparse-tcsh,argparse-zsh,argparse-sh
Classifier: Programming Language :: Python :: 3
Classifier: License :: OSI Approved :: MIT License
Classifier: Operating System :: OS Independent
Requires-Python: >=3.7
License-File: LICENSE
